minigame/__init__.py
minigame/__main__.py
minigame/count.py
minigame/rock_paper_scissor.py
minigame/space_invaders.py
minigame/tempCodeRunnerFile.py
minigame/tictactoe.py
minigame/ttt_o.png
minigame/ttt_x.png
mksv_miniGame-0.1.7.dist-info/LICENSE
mksv_miniGame-0.1.7.dist-info/METADATA
mksv_miniGame-0.1.7.dist-info/WHEEL
mksv_miniGame-0.1.7.dist-info/entry_points.txt
mksv_miniGame-0.1.7.dist-info/top_level.txt
mksv_miniGame-0.1.7.dist-info/RECORD
